main.py
blockbeats_mcp-0.1.0.dist-info/licenses/LICENSE
blockbeats_mcp-0.1.0.dist-info/METADATA
blockbeats_mcp-0.1.0.dist-info/WHEEL
blockbeats_mcp-0.1.0.dist-info/top_level.txt
blockbeats_mcp-0.1.0.dist-info/RECORD
