Metadata-Version: 2.4
Name: blockbeats-mcp
Version: 0.1.0
Summary: An MCP server that delivers blockchain news and in-depth articles from BlockBeats for AI agents.
Requires-Python: >=3.10
License-File: LICENSE
Requires-Dist: httpx>=0.28.1
Requires-Dist: mcp[cli]>=1.6.0
Dynamic: license-file
